{ "compressionlevel":-1,
 "height":13,
 "infinite":false,
 "layers":[
        {
         "data":[13, 13, 13, 13, 13, 13, 13, 13, 13, 13, 13, 13, 13, 13, 13, 13, 13, 13,
            13, 13, 13, 13, 13, 13, 13, 13, 13, 13, 13, 13, 13, 13, 13, 13, 13, 13,
            13, 13, 13, 13, 13, 13, 13, 13, 13, 13, 13, 13, 13, 13, 13, 13, 13, 13,
            13, 13, 13, 13, 13, 13, 13, 13, 13, 13, 13, 13, 13, 13, 13, 13, 13, 13,
            13, 13, 13, 13, 13, 13, 13, 13, 13, 13, 13, 13, 13, 13, 13, 13, 13, 13,
            13, 13, 13, 13, 13, 13, 13, 13, 13, 13, 13, 13, 13, 13, 13, 13, 13, 13,
            13, 13, 13, 13, 13, 13, 13, 13, 13, 13, 13, 13, 13, 13, 13, 13, 13, 13,
            13, 13, 13, 13, 13, 13, 13, 13, 13, 13, 13, 13, 13, 13, 13, 13, 13, 13,
            13, 13, 13, 13, 13, 13, 13, 13, 13, 13, 13, 13, 13, 13, 13, 13, 13, 13,
            13, 13, 13, 13, 13, 13, 13, 13, 13, 13, 13, 13, 13, 13, 13, 13, 13, 13,
            13, 13, 13, 13, 13, 13, 13, 13, 13, 13, 13, 13, 13, 13, 13, 13, 13, 13,
            13, 13, 13, 13, 13, 13, 13, 13, 13, 13, 13, 13, 13, 13, 13, 13, 13, 13,
            13, 13, 13, 13, 13, 13, 13, 13, 13, 13, 13, 13, 13, 13, 13, 13, 13, 13],
         "height":13,
         "id":1,
         "name":"Tile Layer 1",
         "opacity":1,
         "type":"tilelayer",
         "visible":true,
         "width":18,
         "x":0,
         "y":0
        }, 
        {
         "data":[47, 47, 47, 47, 47, 47, 47, 47, 47, 47, 47, 47, 47, 47, 47, 47, 47, 47,
            47, 47, 47, 47, 47, 47, 47, 47, 47, 47, 47, 47, 47, 47, 47, 47, 47, 47,
            0, 0, 0, 0, 0, 0, 0, 0, 0, 0, 0, 0, 0, 0, 0, 0, 0, 0,
            54, 54, 54, 54, 54, 54, 54, 54, 54, 54, 54, 54, 54, 54, 54, 54, 54, 54,
            61, 0, 0, 37, 0, 0, 0, 0, 0, 0, 0, 0, 0, 0, 0, 0, 0, 40,
            0, 0, 36, 0, 0, 0, 0, 0, 0, 0, 0, 0, 0, 0, 0, 0, 0, 0,
            0, 52, 0, 0, 0, 0, 0, 0, 0, 0, 0, 60, 0, 0, 0, 0, 0, 0,
            36, 62, 0, 61, 0, 0, 0, 0, 0, 0, 0, 60, 0, 0, 0, 0, 0, 0,
            0, 0, 37, 0, 0, 0, 0, 0, 0, 0, 0, 60, 0, 0, 0, 0, 0, 40,
            54, 54, 54, 54, 54, 54, 54, 54, 54, 54, 54, 54, 54, 54, 54, 54, 54, 54,
            0, 0, 0, 0, 0, 0, 0, 0, 0, 0, 0, 0, 0, 0, 0, 0, 0, 0,
            47, 47, 47, 47, 47, 47, 47, 47, 47, 47, 47, 47, 47, 47, 47, 47, 47, 47,
            47, 47, 47, 47, 47, 47, 47, 47, 47, 47, 47, 47, 47, 47, 47, 47, 47, 47],
         "height":13,
         "id":3,
         "name":"Collider",
         "opacity":1,
         "type":"tilelayer",
         "visible":true,
         "width":18,
         "x":0,
         "y":0
        }, 
        {
         "data":[0, 0, 0, 0, 0, 0, 0, 0, 0, 0, 0, 0, 0, 0, 0, 0, 0, 0,
            0, 0, 0, 0, 0, 0, 0, 0, 0, 0, 0, 0, 0, 0, 0, 0, 0, 0,
            0, 0, 0, 0, 0, 0, 0, 0, 0, 0, 0, 0, 0, 0, 0, 0, 0, 0,
            0, 0, 0, 0, 0, 0, 0, 0, 0, 0, 0, 0, 0, 0, 0, 0, 0, 0,
            0, 0, 0, 0, 0, 0, 0, 0, 0, 0, 0, 0, 0, 0, 0, 0, 0, 0,
            0, 0, 0, 0, 0, 0, 0, 0, 0, 0, 0, 0, 0, 0, 0, 44, 44, 44,
            0, 0, 0, 0, 0, 0, 0, 0, 0, 0, 0, 0, 0, 0, 0, 44, 44, 44,
            0, 0, 0, 0, 0, 0, 0, 0, 0, 0, 0, 0, 0, 0, 0, 44, 44, 44,
            0, 0, 0, 0, 0, 0, 0, 0, 0, 0, 0, 0, 0, 0, 0, 0, 0, 0,
            0, 0, 0, 0, 0, 0, 0, 0, 0, 0, 0, 0, 0, 0, 0, 0, 0, 0,
            0, 0, 0, 0, 0, 0, 0, 0, 0, 0, 0, 0, 0, 0, 0, 0, 0, 0,
            0, 0, 0, 0, 0, 0, 0, 0, 0, 0, 0, 0, 0, 0, 0, 0, 0, 0,
            0, 0, 0, 0, 0, 0, 0, 0, 0, 0, 0, 0, 0, 0, 0, 0, 0, 0],
         "height":13,
         "id":5,
         "name":"Flower",
         "opacity":1,
         "type":"tilelayer",
         "visible":true,
         "width":18,
         "x":0,
         "y":0
        }, 
        {
         "draworder":"topdown",
         "id":4,
         "name":"Spawn",
         "objects":[
                {
                 "height":0,
                 "id":1,
                 "name":"BeeSpawn",
                 "rotation":0,
                 "type":"",
                 "visible":true,
                 "width":0,
                 "x":119.875,
                 "y":103.875
                }],
         "opacity":1,
         "type":"objectgroup",
         "visible":true,
         "x":0,
         "y":0
        }, 
        {
         "draworder":"topdown",
         "id":7,
         "name":"Enemy",
         "objects":[
                {
                 "height":0,
                 "id":17,
                 "name":"Enemy",
                 "rotation":0,
                 "type":"",
                 "visible":true,
                 "width":0,
                 "x":215.943181818182,
                 "y":71.8181818181818
                }, 
                {
                 "height":0,
                 "id":10,
                 "name":"Enemy",
                 "rotation":0,
                 "type":"",
                 "visible":true,
                 "width":0,
                 "x":151.931818181818,
                 "y":72.1363636363636
                }, 
                {
                 "height":0,
                 "id":18,
                 "name":"Enemy",
                 "rotation":0,
                 "type":"",
                 "visible":true,
                 "width":0,
                 "x":71.6363636363637,
                 "y":87.6590909090909
                }, 
                {
                 "height":0,
                 "id":16,
                 "name":"Enemy",
                 "rotation":0,
                 "type":"",
                 "visible":true,
                 "width":0,
                 "x":216.125,
                 "y":88.5454545454546
                }, 
                {
                 "height":0,
                 "id":11,
                 "name":"Enemy",
                 "rotation":0,
                 "type":"",
                 "visible":true,
                 "width":0,
                 "x":151.931818181818,
                 "y":87.9545454545455
                }, 
                {
                 "height":0,
                 "id":19,
                 "name":"Enemy",
                 "rotation":0,
                 "type":"",
                 "visible":true,
                 "width":0,
                 "x":71.6363636363637,
                 "y":103.477272727273
                }, 
                {
                 "height":0,
                 "id":21,
                 "name":"Enemy",
                 "rotation":0,
                 "type":"",
                 "visible":true,
                 "width":0,
                 "x":71.6363636363637,
                 "y":103.477272727273
                }, 
                {
                 "height":0,
                 "id":15,
                 "name":"Enemy",
                 "rotation":0,
                 "type":"",
                 "visible":true,
                 "width":0,
                 "x":216.125,
                 "y":104.363636363636
                }, 
                {
                 "height":0,
                 "id":12,
                 "name":"Enemy",
                 "rotation":0,
                 "type":"",
                 "visible":true,
                 "width":0,
                 "x":151.9375,
                 "y":104.318181818182
                }, 
                {
                 "height":0,
                 "id":20,
                 "name":"Enemy",
                 "rotation":0,
                 "type":"",
                 "visible":true,
                 "width":0,
                 "x":71.6420454545455,
                 "y":119.840909090909
                }, 
                {
                 "height":0,
                 "id":22,
                 "name":"Enemy",
                 "rotation":0,
                 "type":"",
                 "visible":true,
                 "width":0,
                 "x":71.6420454545455,
                 "y":119.840909090909
                }, 
                {
                 "height":0,
                 "id":23,
                 "name":"Enemy",
                 "rotation":0,
                 "type":"",
                 "visible":true,
                 "width":0,
                 "x":71.6420454545455,
                 "y":135.965909090909
                }, 
                {
                 "height":0,
                 "id":24,
                 "name":"Enemy",
                 "rotation":0,
                 "type":"",
                 "visible":true,
                 "width":0,
                 "x":71.6647727272727,
                 "y":72.1022727272727
                }],
         "opacity":1,
         "type":"objectgroup",
         "visible":true,
         "x":0,
         "y":0
        }, 
        {
         "draworder":"topdown",
         "id":6,
         "name":"FlowerZoom",
         "objects":[
                {
                 "height":0,
                 "id":4,
                 "name":"CameraZoom",
                 "rotation":0,
                 "type":"",
                 "visible":true,
                 "width":0,
                 "x":263.839015151515,
                 "y":103.846590909091
                }],
         "opacity":1,
         "type":"objectgroup",
         "visible":true,
         "x":0,
         "y":0
        }],
 "nextlayerid":8,
 "nextobjectid":25,
 "orientation":"orthogonal",
 "renderorder":"right-down",
 "tiledversion":"1.11.2",
 "tileheight":16,
 "tilesets":[
        {
         "firstgid":1,
         "source":"..\/..\/Background.tsx"
        }, 
        {
         "firstgid":33,
         "source":"..\/..\/Decoration.tsx"
        }],
 "tilewidth":16,
 "type":"map",
 "version":"1.10",
 "width":18
}